cykooz/__init__.py
cykooz/testing/__init__.py
cykooz/testing/runtests.py
cykooz_testing-2.1.dist-info/METADATA
cykooz_testing-2.1.dist-info/WHEEL
cykooz_testing-2.1.dist-info/entry_points.txt
cykooz_testing-2.1.dist-info/top_level.txt
cykooz_testing-2.1.dist-info/RECORD
